{"id":27,"id64":10477373803,"name":"Sol","url":"https:\/\/www.edsm.net\/en\/system\/bodies\/id\/27\/name\/Sol","bodies":[{"id":3794,"id64":10477373803,"bodyId":0,"name":"Sol","discovery":{"commander":"Mini Valentine","date":"2017-09-29 20:09:09"},"type":"Star","subType":"G (White-Yellow) Star","offset":0,"parents":null,"distanceToArrival":0,"isMainStar":true,"isScoopable":true,"age":4792,"luminosity":"V","absoluteMagnitude":4.829987,"solarMasses":1,"solarRadius":0.9999999539899354,"surfaceTemperature":5778,"orbitalPeriod":null,"semiMajorAxis":null,"orbitalEccentricity":null,"orbitalInclination":null,"argOfPeriapsis":null,"rotationalPeriod":2.583274558738426,"rotationalPeriodTidallyLocked":false,"axialTilt":"-0.219615","belts":[{"name":"Asteroid Belt","type":"Rocky","mass":608900000000,"innerRadius":308170000,"outerRadius":489190000}],"updateTime":"2018-03-28 17:59:11"},{"id":11236,"id64":36028807496337771,"bodyId":1,"name":"Mercury","discovery":{"commander":"Mini Valentine","date":"2017-09-29 20:09:09"},"type":"Planet","subType":"Metal-rich body","offset":1,"parents":[{"Star":0}],"distanceToArrival":156.695618,"isLandable":true,"gravity":0.37588835103398993,"earthMasses":0.055,"radius":2439.7,"surfaceTemperature":401,"surfacePressure":null,"volcanismType":"No volcanism","atmosphereType":"No atmosphere","atmosphereComposition":null,"solidComposition":{"Metal":60,"Rock":40,"Ice":0},"terraformingState":"Not terraformable","orbitalPeriod":87.96910300925926,"semiMajorAxis":0.3870983729984333,"orbitalEccentricity":0.2056,"orbitalInclination":7,"argOfPeriapsis":29.124001,"rotationalPeriod":58.646001157407404,"rotationalPeriodTidallyLocked":false,"axialTilt":"0.036826","materials":{"Iron":23.5085,"Nickel":17.7808,"Sulphur":12.8564,"Carbon":10.8109,"Chromium":10.5725,"Manganese":9.70875,"Phosphorus":6.92134,"Germanium":3.80609,"Tin":1.55628,"Ruthenium":1.4518,"Mercury":1.02658},"updateTime":"2018-06-10 18:48:03"},{"id":10217,"id64":72057604515301739,"bodyId":2,"name":"Venus","discovery":{"commander":"Mini Valentine","date":"2017-09-29 20:09:09"},"type":"Planet","subType":"High metal content world","offset":1,"parents":[{"Star":0}],"distanceToArrival":359.277496,"isLandable":false,"gravity":0.9052270113450551,"earthMasses":0.815,"radius":6051.8,"surfaceTemperature":735,"surfacePressure":93.18950900567481,"volcanismType":"Minor Rocky Magma","atmosphereType":"Hot thick Carbon dioxide","atmosphereComposition":{"Carbon dioxide":96.5,"Nitrogen":3.5},"solidComposition":{"Rock":70,"Metal":30,"Ice":0},"terraformingState":"Not terraformable","orbitalPeriod":224.70099537037038,"semiMajorAxis":0.7233256732710969,"orbitalEccentricity":0.0067,"orbitalInclination":3.395,"argOfPeriapsis":55.186001,"rotationalPeriod":243.01849537037037,"rotationalPeriodTidallyLocked":true,"axialTilt":"3.094469","updateTime":"2018-06-10 18:48:03"},{"id":7497,"id64":108086401534265707,"bodyId":3,"name":"Earth","discovery":{"commander":"Mini Valentine","date":"2017-09-29 20:09:09"},"type":"Planet","subType":"Earth-like world","offset":1,"parents":[{"Star":0}],"distanceToArrival":490.767761,"isLandable":false,"gravity":0.9999686429450564,"earthMasses":1,"radius":6378.1,"surfaceTemperature":288,"surfacePressure":0.9990787688132248,"volcanismType":"Rocky Magma","atmosphereType":"Suitable for water-based life","atmosphereComposition":{"Nitrogen":77.8864,"Oxygen":20.893,"Argon":0.931637},"solidComposition":{"Rock":70,"Metal":30,"Ice":0},"terraformingState":"Not terraformable","orbitalPeriod":365.25636574074076,"semiMajorAxis":1.0000007214273805,"orbitalEccentricity":0.0167,"orbitalInclination":0,"argOfPeriapsis":114.207832,"rotationalPeriod":0.9972697844328704,"rotationalPeriodTidallyLocked":false,"axialTilt":"0.401426","updateTime":"2018-06-10 18:48:03"},{"id":14780,"id64":144115198553229675,"bodyId":4,"name":"Moon","discovery":{"commander":"Mini Valentine","date":"2017-09-29 20:09:09"},"type":"Planet","subType":"Rocky body","offset":2,"parents":[{"Planet":3},{"Star":0}],"distanceToArrival":489.988129,"isLandable":false,"gravity":0.16567075215550864,"earthMasses":0.012304,"radius":1738.14,"surfaceTemperature":250,"surfacePressure":null,"volcanismType":"No volcanism","atmosphereType":"No atmosphere","atmosphereComposition":null,"solidComposition":{"Rock":80,"Metal":20,"Ice":0},"terraformingState":"Not terraformable","orbitalPeriod":27.32158275462963,"semiMajorAxis":0.0025695482308759894,"orbitalEccentricity":0.0549,"orbitalInclination":23.434999,"argOfPeriapsis":0,"rotationalPeriod":27.32158275462963,"rotationalPeriodTidallyLocked":true,"axialTilt":"0.11671","updateTime":"2018-06-10 18:48:03"},{"id":1828,"id64":180143995572193643,"bodyId":5,"name":"Mars","discovery":{"commander":"Mini Valentine","date":"2017-09-29 20:09:09"},"type":"Planet","subType":"Earth-like world","offset":1,"parents":[{"Star":0}],"distanceToArrival":705.626587,"isLandable":false,"gravity":0.3773690618814674,"earthMasses":0.107,"radius":3396.2,"surfaceTemperature":260,"surfacePressure":2.303390698248211,"volcanismType":"No volcanism","atmosphereType":"Suitable for water-based life","atmosphereComposition":{"Nitrogen":91.1699,"Oxygen":8.68285,"Water":0.095125},"solidComposition":{"Rock":70,"Metal":30,"Ice":0},"terraformingState":"Terraformed","orbitalPeriod":686.9710185185185,"semiMajorAxis":1.5236785990430544,"orbitalEccentricity":0.0934,"orbitalInclination":1.85,"argOfPeriapsis":286.536987,"rotationalPeriod":1.02595703125,"rotationalPeriodTidallyLocked":false,"axialTilt":"0.439648","updateTime":"2018-06-10 18:48:03"},{"id":48,"id64":252201589610121579,"bodyId":7,"name":"Jupiter","discovery":{"commander":"Mini Valentine","date":"2017-09-29 20:09:09"},"type":"Planet","subType":"Class I gas giant","offset":1,"parents":[{"Star":0}],"distanceToArrival":2649.656738,"isLandable":false,"gravity":2.5293417504360067,"earthMasses":317.799622,"radius":71492,"surfaceTemperature":147,"surfacePressure":null,"volcanismType":"No volcanism","atmosphereType":"No atmosphere","atmosphereComposition":{"Hydrogen":73.6995,"Helium":26.3005},"solidComposition":null,"terraformingState":"Not terraformable","orbitalPeriod":4332.58962962963,"semiMajorAxis":5.204265930076503,"orbitalEccentricity":0.048775,"orbitalInclination":1.305,"argOfPeriapsis":275.06601,"rotationalPeriod":0.41354166666666664,"rotationalPeriodTidallyLocked":false,"axialTilt":"0.054629","rings":[{"name":"Jupiter Halo Ring","type":"Rocky","mass":10000,"innerRadius":92000,"outerRadius":182000}],"reserveLevel":"Common","updateTime":"2018-06-10 18:48:03"},{"id":13971,"id64":324259183648049515,"bodyId":9,"name":"Io","discovery":{"commander":"Mini Valentine","date":"2017-09-29 20:09:09"},"type":"Planet","subType":"Rocky body","offset":2,"parents":[{"Planet":7},{"Star":0}],"distanceToArrival":2650.213135,"isLandable":false,"gravity":0.1839489502155097,"earthMasses":0.015,"radius":1821.3,"surfaceTemperature":120,"surfacePressure":0,"volcanismType":"Major Rocky Magma","atmosphereType":"Sulphur dioxide","atmosphereComposition":{"Sulphur dioxide":90,"Silicates":5,"Oxygen":3},"solidComposition":{"Rock":80,"Metal":20,"Ice":0},"terraformingState":"Not terraformable","orbitalPeriod":1.7691377314814816,"semiMajorAxis":0.002818889961647028,"orbitalEccentricity":0.0041,"orbitalInclination":0.05,"argOfPeriapsis":0,"rotationalPeriod":1.7691377314814816,"rotationalPeriodTidallyLocked":true,"axialTilt":"0","updateTime":"2018-06-10 18:48:03"},{"id":6371,"id64":360287980667013483,"bodyId":10,"name":"Europa","discovery":{"commander":"Mini Valentine","date":"2017-09-29 20:09:09"},"type":"Planet","subType":"Icy body","offset":2,"parents":[{"Planet":7},{"Star":0}],"distanceToArrival":2647.554199,"isLandable":true,"gravity":0.13358709447585793,"earthMasses":0.008,"radius":1560.8,"surfaceTemperature":104,"surfacePressure":null,"volcanismType":"Major Water Magma","atmosphereType":"No atmosphere","atmosphereComposition":null,"solidComposition":{"Ice":60.0018,"Rock":26.934399999999997,"Metal":13.0638},"terraformingState":"Not terraformable","orbitalPeriod":3.5511809172453703,"semiMajorAxis":0.0044846888586095365,"orbitalEccentricity":0.009,"orbitalInclination":0.47,"argOfPeriapsis":0,"rotationalPeriod":3.5511812789351853,"rotationalPeriodTidallyLocked":true,"axialTilt":"0","materials":{"Sulphur":22.5553,"Carbon":18.9667,"Iron":16.95,"Nickel":12.8203,"Phosphorus":12.1428,"Chromium":7.623,"Vanadium":4.16234,"Arsenic":1.59986,"Cadmium":1.31625,"Molybdenum":1.10683,"Antimony":0.756526},"updateTime":"2018-06-10 18:48:03"},{"id":11998,"id64":396316777685977451,"bodyId":11,"name":"Ganymede","discovery":{"commander":"Mini Valentine","date":"2017-09-29 20:09:09"},"type":"Planet","subType":"Rocky body","offset":2,"parents":[{"Planet":7},{"Star":0}],"distanceToArrival":2647.685547,"isLandable":true,"gravity":0.145479329590787,"earthMasses":0.024814,"radius":2634.1,"surfaceTemperature":116,"surfacePressure":null,"volcanismType":"No volcanism","atmosphereType":"No atmosphere","atmosphereComposition":null,"solidComposition":{"Rock":80,"Metal":20,"Ice":0},"terraformingState":"Not terraformable","orbitalPeriod":7.154552951388889,"semiMajorAxis":0.007155180772235417,"orbitalEccentricity":0.0013,"orbitalInclination":0.2,"argOfPeriapsis":0,"rotationalPeriod":7.154552951388889,"rotationalPeriodTidallyLocked":true,"axialTilt":"0.00576","materials":{"Iron":21.536,"Sulphur":17.7255,"Nickel":16.2889,"Carbon":14.9053,"Phosphorus":9.54265,"Manganese":8.89414,"Germanium":5.24756,"Zirconium":2.50077,"Molybdenum":1.40629,"Tungsten":1.18254,"Technetium":0.770255},"updateTime":"2018-06-10 18:48:03"},{"id":12912,"id64":432345574704941419,"bodyId":12,"name":"Callisto","discovery":{"commander":"Mini Valentine","date":"2017-09-29 20:09:09"},"type":"Planet","subType":"Rocky body","offset":2,"parents":[{"Planet":7},{"Star":0}],"distanceToArrival":2644.818848,"isLandable":true,"gravity":0.12618081199428388,"earthMasses":0.018016,"radius":2410,"surfaceTemperature":114,"surfacePressure":null,"volcanismType":"No volcanism","atmosphereType":"No atmosphere","atmosphereComposition":null,"solidComposition":{"Rock":80,"Metal":20,"Ice":0},"terraformingState":"Not terraformable","orbitalPeriod":16.68901765046296,"semiMajorAxis":0.012585069822120135,"orbitalEccentricity":0.0074,"orbitalInclination":0.192,"argOfPeriapsis":0,"rotationalPeriod":16.68901765046296,"rotationalPeriodTidallyLocked":true,"axialTilt":"0","materials":{"Iron":20.4631,"Sulphur":16.8424,"Nickel":15.4774,"Carbon":14.1627,"Chromium":9.20291,"Phosphorus":9.06723,"Manganese":8.45103,"Zirconium":2.37618,"Niobium":1.39854,"Molybdenum":1.33623,"Yttrium":1.22223},"updateTime":"2018-06-10 18:48:03"},{"id":5240,"id64":468374371723905387,"bodyId":13,"name":"Saturn","discovery":{"commander":"Mini Valentine","date":"2017-09-29 20:09:09"},"type":"Planet","subType":"Class I gas giant","offset":1,"parents":[{"Star":0}],"distanceToArrival":4767.641602,"isLandable":false,"gravity":1.1120262414010167,"earthMasses":95.159035,"radius":59000,"surfaceTemperature":87,"surfacePressure":null,"volcanismType":"No volcanism","atmosphereType":"No atmosphere","atmosphereComposition":{"Hydrogen":73.6995,"Helium":26.3005},"solidComposition":null,"terraformingState":"Not terraformable","orbitalPeriod":10759.22,"semiMajorAxis":9.582015635788057,"orbitalEccentricity":0.055723,"orbitalInclination":2.48524,"argOfPeriapsis":336.013855,"rotationalPeriod":0.4404166666666667,"rotationalPeriodTidallyLocked":false,"axialTilt":"0.466527","rings":[{"name":"D Ring","type":"Icy","mass":250560,"innerRadius":74500,"outerRadius":140180}],"reserveLevel":"Common","updateTime":"2018-06-10 18:48:03"},{"id":6847,"id64":540431965761833323,"bodyId":15,"name":"Enceladus","discovery":{"commander":"Mini Valentine","date":"2017-09-29 20:09:09"},"type":"Planet","subType":"Icy body","offset":2,"parents":[{"Planet":13},{"Star":0}],"distanceToArrival":4767.709961,"isLandable":true,"gravity":0.011521150334020883,"earthMasses":1.8e-5,"radius":252.1,"surfaceTemperature":73,"surfacePressure":null,"volcanismType":"Major Water Geysers","atmosphereType":"No atmosphere","atmosphereComposition":null,"solidComposition":{"Ice":60.0018,"Rock":26.934399999999997,"Metal":13.0638},"terraformingState":"Not terraformable","orbitalPeriod":1.3702180085416666,"semiMajorAxis":0.0015905838157093501,"orbitalEccentricity":0.0047,"orbitalInclination":0.019,"argOfPeriapsis":0,"rotationalPeriod":1.3702180085416666,"rotationalPeriodTidallyLocked":true,"axialTilt":"0","materials":{"Sulphur":21.3299,"Carbon":17.9362,"Iron":16.0291,"Nickel":12.1238,"Phosphorus":11.4831,"Chromium":7.20883,"Manganese":6.61986,"Zinc":4.35611,"Tin":1.04312,"Ruthenium":0.9899,"Tungsten":0.88016},"updateTime":"2018-06-10 18:48:03"},{"id":7393,"id64":576460762780797291,"bodyId":16,"name":"Tethys","discovery":{"commander":"Mini Valentine","date":"2017-09-29 20:09:09"},"type":"Planet","subType":"Icy body","offset":2,"parents":[{"Planet":13},{"Star":0}],"distanceToArrival":4768.435059,"isLandable":true,"gravity":0.014854349968576637,"earthMasses":0.000103,"radius":531.1,"surfaceTemperature":73,"surfacePressure":null,"volcanismType":"Major Water Geysers","atmosphereType":"No atmosphere","atmosphereComposition":null,"solidComposition":{"Ice":60.0018,"Rock":26.934399999999997,"Metal":13.0638},"terraformingState":"Not terraformable","orbitalPeriod":1.8878020109953704,"semiMajorAxis":0.0019694059990387285,"orbitalEccentricity":0.0001,"orbitalInclination":1.12,"argOfPeriapsis":0,"rotationalPeriod":1.8878020109953704,"rotationalPeriodTidallyLocked":true,"axialTilt":"0","materials":{"Sulphur":24.1107,"Carbon":20.2746,"Iron":18.1189,"Nickel":13.7044,"Phosphorus":12.9801,"Selenium":3.77353,"Zirconium":2.10397,"Arsenic":1.71018,"Niobium":1.23833,"Tungsten":0.994908,"Tellurium":0.990443},"updateTime":"2018-06-10 18:48:03"},{"id":4955,"id64":612489559799761259,"bodyId":17,"name":"Dione","discovery":{"commander":"Mini Valentine","date":"2017-09-29 20:09:09"},"type":"Planet","subType":"Icy body","offset":2,"parents":[{"Planet":13},{"Star":0}],"distanceToArrival":4768.740234,"isLandable":true,"gravity":0.023619750346765285,"earthMasses":0.000183,"radius":561.4,"surfaceTemperature":73,"surfacePressure":null,"volcanismType":"Water Geysers","atmosphereType":"No atmosphere","atmosphereComposition":null,"solidComposition":{"Ice":60.0018,"Rock":26.934399999999997,"Metal":13.0638},"terraformingState":"Not terraformable","orbitalPeriod":2.7369151475694444,"semiMajorAxis":0.0025227360137820465,"orbitalEccentricity":0.0022,"orbitalInclination":0.019,"argOfPeriapsis":0,"rotationalPeriod":19.158405671296297,"rotationalPeriodTidallyLocked":false,"axialTilt":"0","materials":{"Sulphur":21.9984,"Carbon":18.4984,"Iron":16.5315,"Nickel":12.5038,"Phosphorus":11.843,"Chromium":7.43479,"Manganese":6.82736,"Zirconium":1.91965,"Niobium":1.12984,"Mercury":0.721905,"Technetium":0.591267},"updateTime":"2018-06-10 18:48:03"},{"id":10450,"id64":648518356818725227,"bodyId":18,"name":"Rhea","discovery":{"commander":"Mini Valentine","date":"2017-09-29 20:09:09"},"type":"Planet","subType":"Icy body","offset":2,"parents":[{"Planet":13},{"Star":0}],"distanceToArrival":4767.557617,"isLandable":true,"gravity":0.02691516375208343,"earthMasses":0.000386,"radius":763.8,"surfaceTemperature":73,"surfacePressure":null,"volcanismType":"No volcanism","atmosphereType":"No atmosphere","atmosphereComposition":null,"solidComposition":{"Ice":60.0018,"Rock":26.934399999999997,"Metal":13.0638},"terraformingState":"Not terraformable","orbitalPeriod":4.518211805555556,"semiMajorAxis":0.003523498707124312,"orbitalEccentricity":0.001258,"orbitalInclination":0.345,"argOfPeriapsis":0,"rotationalPeriod":4.518211805555556,"rotationalPeriodTidallyLocked":true,"axialTilt":"0","materials":{"Sulphur":22.0767,"Carbon":18.5642,"Iron":16.5903,"Nickel":12.5482,"Phosphorus":11.8851,"Manganese":6.85164,"Zinc":4.50863,"Vanadium":4.07401,"Molybdenum":1.08334,"Tungsten":0.910976,"Tellurium":0.906888},"updateTime":"2018-06-10 18:48:03"},{"id":5154,"id64":684547153837689195,"bodyId":19,"name":"Titan","discovery":{"commander":"Mini Valentine","date":"2017-09-29 20:09:09"},"type":"Planet","subType":"Rocky Ice world","offset":2,"parents":[{"Planet":13},{"Star":0}],"distanceToArrival":4764.810547,"isLandable":false,"gravity":0.13792421732077756,"earthMasses":0.022499,"radius":2576,"surfaceTemperature":94,"surfacePressure":1.0027463453047125,"volcanismType":"Minor Water Magma","atmosphereType":"Thick Methane-rich","atmosphereComposition":{"Nitrogen":98.4,"Methane":1.6},"solidComposition":{"Rock":40.4022,"Ice":40.001799999999996,"Metal":19.596},"terraformingState":"Not terraformable","orbitalPeriod":15.94499855324074,"semiMajorAxis":0.008167695290598811,"orbitalEccentricity":0.0288,"orbitalInclination":0.34854,"argOfPeriapsis":0,"rotationalPeriod":111.615,"rotationalPeriodTidallyLocked":false,"axialTilt":"0","updateTime":"2018-06-10 18:48:03"},{"id":1621,"id64":720575950856653163,"bodyId":20,"name":"Iapetus","discovery":{"commander":"Mini Valentine","date":"2017-09-29 20:09:09"},"type":"Planet","subType":"Rocky body","offset":2,"parents":[{"Planet":13},{"Star":0}],"distanceToArrival":4766.65918,"isLandable":true,"gravity":0.02277153844392925,"earthMasses":0.000302,"radius":734.5,"surfaceTemperature":81,"surfacePressure":null,"volcanismType":"No volcanism","atmosphereType":"No atmosphere","atmosphereComposition":null,"solidComposition":{"Rock":80,"Metal":20,"Ice":0},"terraformingState":"Not terraformable","orbitalPeriod":79.32150462962963,"semiMajorAxis":0.02380260788030053,"orbitalEccentricity":0.028613,"orbitalInclination":15.47,"argOfPeriapsis":0,"rotationalPeriod":79.32150462962963,"rotationalPeriodTidallyLocked":true,"axialTilt":"0","materials":{"Iron":20.029,"Sulphur":16.4852,"Nickel":15.1491,"Carbon":13.8623,"Chromium":9.00769,"Phosphorus":8.87489,"Manganese":8.27176,"Germanium":4.88035,"Niobium":1.36887,"Yttrium":1.19631,"Mercury":0.874632},"updateTime":"2018-06-10 18:48:03"},{"id":11649,"id64":792633544894581099,"bodyId":22,"name":"Uranus","discovery":{"commander":"Mini Valentine","date":"2017-09-29 20:09:09"},"type":"Planet","subType":"Class I gas giant","offset":1,"parents":[{"Star":0}],"distanceToArrival":9191.400391,"isLandable":false,"gravity":0.9053919113722684,"earthMasses":14.539695,"radius":25559,"surfaceTemperature":56,"surfacePressure":null,"volcanismType":"No volcanism","atmosphereType":"No atmosphere","atmosphereComposition":{"Hydrogen":73.6995,"Helium":26.3005},"solidComposition":null,"terraformingState":"Not terraformable","orbitalPeriod":30687.149629629628,"semiMajorAxis":19.229408742861203,"orbitalEccentricity":0.04722,"orbitalInclination":0.772556,"argOfPeriapsis":96.998856,"rotationalPeriod":0.7183300329166666,"rotationalPeriodTidallyLocked":false,"axialTilt":"1.706408","rings":[{"name":"ZetaCC Ring","type":"Icy","mass":46917,"innerRadius":30890,"outerRadius":103000}],"reserveLevel":"Common","updateTime":"2018-06-10 18:48:03"},{"id":5094,"id64":864691138932509035,"bodyId":24,"name":"Ariel","discovery":{"commander":"Mini Valentine","date":"2017-09-29 20:09:09"},"type":"Planet","subType":"Rocky body","offset":2,"parents":[{"Planet":22},{"Star":0}],"distanceToArrival":9191.254883,"isLandable":true,"gravity":0.027554198826164108,"earthMasses":0.000227,"radius":578.9,"surfaceTemperature":57,"surfacePressure":null,"volcanismType":"No volcanism","atmosphereType":"No atmosphere","atmosphereComposition":null,"solidComposition":{"Rock":80,"Metal":20,"Ice":0},"terraformingState":"Not terraformable","orbitalPeriod":2.52,"semiMajorAxis":0.0012768896181889306,"orbitalEccentricity":0.0012,"orbitalInclination":0.26,"argOfPeriapsis":0,"rotationalPeriod":2.52,"rotationalPeriodTidallyLocked":true,"axialTilt":"0","materials":{"Iron":20.5526,"Sulphur":16.9162,"Nickel":15.5451,"Carbon":14.2247,"Chromium":9.24319,"Phosphorus":9.10692,"Manganese":8.48802,"Zirconium":2.38658,"Molybdenum":1.34207,"Tellurium":1.29707,"Mercury":0.897499},"updateTime":"2018-06-10 18:48:03"},{"id":8425,"id64":900719935951473003,"bodyId":25,"name":"Umbriel","discovery":{"commander":"Mini Valentine","date":"2017-09-29 20:09:09"},"type":"Planet","subType":"Icy body","offset":2,"parents":[{"Planet":22},{"Star":0}],"distanceToArrival":9191.498047,"isLandable":true,"gravity":0.02332163067402972,"earthMasses":0.000196,"radius":584.7,"surfaceTemperature":50,"surfacePressure":null,"volcanismType":"No volcanism","atmosphereType":"No atmosphere","atmosphereComposition":null,"solidComposition":{"Ice":60.0018,"Rock":26.934399999999997,"Metal":13.0638},"terraformingState":"Not terraformable","orbitalPeriod":4.143999927662037,"semiMajorAxis":0.0017780998536632245,"orbitalEccentricity":0.0039,"orbitalInclination":0.128,"argOfPeriapsis":0,"rotationalPeriod":4.144000289351852,"rotationalPeriodTidallyLocked":true,"axialTilt":"0","materials":{"Sulphur":22.0552,"Carbon":18.5462,"Iron":16.5742,"Nickel":12.536,"Phosphorus":11.8736,"Chromium":7.45398,"Zinc":4.50425,"Germanium":3.49807,"Cadmium":1.28706,"Tin":1.07859,"Technetium":0.592793},"updateTime":"2018-06-10 18:48:03"},{"id":910,"id64":936748732970436971,"bodyId":26,"name":"Titania","discovery":{"commander":"Mini Valentine","date":"2017-09-29 20:09:09"},"type":"Planet","subType":"Icy body","offset":2,"parents":[{"Planet":22},{"Star":0}],"distanceToArrival":9192.62793,"isLandable":true,"gravity":0.03867793502359556,"earthMasses":0.000591,"radius":788.4,"surfaceTemperature":50,"surfacePressure":null,"volcanismType":"No volcanism","atmosphereType":"No atmosphere","atmosphereComposition":null,"solidComposition":{"Ice":60.0018,"Rock":26.934399999999997,"Metal":13.0638},"terraformingState":"Not terraformable","orbitalPeriod":8.706234085648148,"semiMajorAxis":0.0029138778377010683,"orbitalEccentricity":0.0011,"orbitalInclination":0.34,"argOfPeriapsis":0,"rotationalPeriod":8.706234085648148,"rotationalPeriodTidallyLocked":true,"axialTilt":"0","materials":{"Sulphur":23.42,"Carbon":19.6938,"Iron":17.5998,"Nickel":13.3118,"Phosphorus":12.6083,"Zinc":4.78298,"Selenium":3.66543,"Arsenic":1.66119,"Molybdenum":1.14926,"Tin":1.14533,"Tellurium":0.962071},"updateTime":"2018-06-10 18:48:03"},{"id":158,"id64":972777529989400939,"bodyId":27,"name":"Oberon","discovery":{"commander":"Mini Valentine","date":"2017-09-29 20:09:09"},"type":"Planet","subType":"Rocky body","offset":2,"parents":[{"Planet":22},{"Star":0}],"distanceToArrival":9192.368164,"isLandable":true,"gravity":0.03543518161455724,"earthMasses":0.000505,"radius":761.4,"surfaceTemperature":57,"surfacePressure":null,"volcanismType":"No volcanism","atmosphereType":"No atmosphere","atmosphereComposition":null,"solidComposition":{"Rock":80,"Metal":20,"Ice":0},"terraformingState":"Not terraformable","orbitalPeriod":13.463233506944444,"semiMajorAxis":0.0039005898497725074,"orbitalEccentricity":0.0014,"orbitalInclination":0.058,"argOfPeriapsis":0,"rotationalPeriod":13.463233506944444,"rotationalPeriodTidallyLocked":true,"axialTilt":"0","materials":{"Iron":20.4545,"Sulphur":16.8354,"Nickel":15.4709,"Carbon":14.1568,"Chromium":9.19905,"Phosphorus":9.06343,"Zinc":5.55875,"Germanium":4.98403,"Cadmium":1.58838,"Niobium":1.39795,"Tellurium":1.29087},"updateTime":"2018-06-10 18:48:03"},{"id":9994,"id64":1008806327008364907,"bodyId":28,"name":"Neptune","discovery":{"commander":"Mini Valentine","date":"2017-09-29 20:09:09"},"type":"Planet","subType":"Class I gas giant","offset":1,"parents":[{"Star":0}],"distanceToArrival":14880.661133,"isLandable":false,"gravity":1.1375812407013925,"earthMasses":17.149639,"radius":24764,"surfaceTemperature":45,"surfacePressure":null,"volcanismType":"No volcanism","atmosphereType":"No atmosphere","atmosphereComposition":{"Hydrogen":73.6995,"Helium":26.3005},"solidComposition":null,"terraformingState":"Not terraformable","orbitalPeriod":60190.03259259259,"semiMajorAxis":29.809943509790877,"orbitalEccentricity":0.008678,"orbitalInclination":1.767975,"argOfPeriapsis":273.219421,"rotationalPeriod":0.6713000036226852,"rotationalPeriodTidallyLocked":false,"axialTilt":"0.494277","rings":[{"name":"Galle Ring","type":"Icy","mass":11077,"innerRadius":40900,"outerRadius":57200}],"reserveLevel":"Common","updateTime":"2018-06-10 18:48:03"},{"id":9188,"id64":1080863921046292843,"bodyId":30,"name":"Triton","discovery":{"commander":"Mini Valentine","date":"2017-09-29 20:09:09"},"type":"Planet","subType":"Icy body","offset":2,"parents":[{"Planet":28},{"Star":0}],"distanceToArrival":14880.037109,"isLandable":true,"gravity":0.07972804851489296,"earthMasses":0.00359,"radius":1353.4,"surfaceTemperature":40,"surfacePressure":null,"volcanismType":"No volcanism","atmosphereType":"No atmosphere","atmosphereComposition":null,"solidComposition":{"Ice":60.0018,"Rock":26.934399999999997,"Metal":13.0638},"terraformingState":"Not terraformable","orbitalPeriod":-5.876854021990741,"semiMajorAxis":0.0023714170685719526,"orbitalEccentricity":1.6e-5,"orbitalInclination":-23.115,"argOfPeriapsis":0,"rotationalPeriod":-5.876854021990741,"rotationalPeriodTidallyLocked":false,"axialTilt":null,"materials":{"Sulphur":22.5769,"Carbon":18.9848,"Iron":16.9662,"Nickel":12.8325,"Phosphorus":12.1544,"Chromium":7.63027,"Vanadium":4.16631,"Arsenic":1.60138,"Molybdenum":1.10788,"Ruthenium":1.04777,"Tungsten":0.931615},"updateTime":"2018-06-10 18:48:03"},{"id":2394,"id64":1152921515084220779,"bodyId":32,"name":"Pluto","discovery":{"commander":"Mini Valentine","date":"2017-09-29 20:09:09"},"type":"Planet","subType":"Rocky body","offset":1,"parents":[{"Null":31},{"Star":0}],"distanceToArrival":21379.697266,"isLandable":false,"gravity":0.06670630868303133,"earthMasses":0.00218,"radius":1153,"surfaceTemperature":55,"surfacePressure":0.0040684993042190976,"volcanismType":"Minor Methane Magma","atmosphereType":"Thin Methane","atmosphereComposition":{"Methane":50,"Nitrogen":50},"solidComposition":{"Rock":80,"Metal":20,"Ice":0},"terraformingState":"Not terraformable","orbitalPeriod":6.393943865740741,"semiMajorAxis":1.3596588911876806e-5,"orbitalEccentricity":0,"orbitalInclination":0.001,"argOfPeriapsis":0,"rotationalPeriod":6.387000144675926,"rotationalPeriodTidallyLocked":false,"axialTilt":"2.086209","updateTime":"2018-06-10 18:48:03"},{"id":7065,"id64":1188950312103184747,"bodyId":33,"name":"Charon","discovery":{"commander":"Mini Valentine","date":"2017-09-29 20:09:09"},"type":"Planet","subType":"Rocky body","offset":1,"parents":[{"Null":31},{"Star":0}],"distanceToArrival":21379.697266,"isLandable":true,"gravity":0.02825758236303145,"earthMasses":0.000253,"radius":603.5,"surfaceTemperature":39,"surfacePressure":null,"volcanismType":"No volcanism","atmosphereType":"No atmosphere","atmosphereComposition":null,"solidComposition":{"Rock":80,"Metal":20,"Ice":0},"terraformingState":"Not terraformable","orbitalPeriod":6.393943865740741,"semiMajorAxis":0.0001172274439331308,"orbitalEccentricity":0,"orbitalInclination":0.001,"argOfPeriapsis":180,"rotationalPeriod":6.387000144675926,"rotationalPeriodTidallyLocked":true,"axialTilt":"0","materials":{"Iron":21.1635,"Sulphur":17.419,"Nickel":16.0072,"Carbon":14.6476,"Chromium":9.51794,"Phosphorus":9.37762,"Zinc":5.75146,"Zirconium":2.45752,"Cadmium":1.64344,"Antimony":1.09053,"Mercury":0.924177},"updateTime":"2018-06-10 18:48:03"},{"id":3200642,"id64":1224979109122148715,"bodyId":34,"name":"90482 Orcus","discovery":{"commander":"Mini Valentine","date":"2017-09-29 20:09:09"},"type":"Planet","subType":"Rocky Ice world","offset":1,"parents":[{"Star":0}],"distanceToArrival":19397.138672,"isLandable":true,"gravity":0.005176236801765751,"earthMasses":0.000107,"radius":917,"surfaceTemperature":35,"surfacePressure":null,"volcanismType":"No volcanism","atmosphereType":"No atmosphere","atmosphereComposition":null,"solidComposition":{"Rock":40.4022,"Ice":40.001799999999996,"Metal":19.596},"terraformingState":null,"orbitalPeriod":1735.79,"semiMajorAxis":39.46902900146693,"orbitalEccentricity":0.21799,"orbitalInclination":44.044498,"argOfPeriapsis":105.460564,"rotationalPeriod":0.5495000090393518,"rotationalPeriodTidallyLocked":false,"axialTilt":"0.258117","materials":{"Sulphur":20.061,"Iron":18.0168,"Carbon":16.8693,"Nickel":13.6272,"Phosphorus":10.8,"Chromium":8.10277,"Manganese":7.44077,"Zirconium":2.09213,"Cadmium":1.39909,"Antimony":0.80414,"Mercury":0.786766},"updateTime":"2018-06-10 18:48:03"},{"id":8136010,"id64":1261007906141112683,"bodyId":35,"name":"Vanth","discovery":{"commander":"Mini Valentine","date":"2017-09-29 20:09:09"},"type":"Planet","subType":"Rocky Ice world","offset":2,"parents":[{"Planet":34},{"Star":0}],"distanceToArrival":19397.162109,"isLandable":true,"gravity":0.003738082703213611,"earthMasses":7.0e-6,"radius":276,"surfaceTemperature":35,"surfacePressure":null,"volcanismType":"No volcanism","atmosphereType":"No atmosphere","atmosphereComposition":null,"solidComposition":{"Rock":40.4022,"Ice":40.001799999999996,"Metal":19.596},"terraformingState":null,"orbitalPeriod":9.54,"semiMajorAxis":6.036181502949694e-5,"orbitalEccentricity":0.007,"orbitalInclination":21,"argOfPeriapsis":227.519165,"rotationalPeriod":9.540862991898148,"rotationalPeriodTidallyLocked":true,"axialTilt":"0.490645","materials":{"Sulphur":21.414,"Iron":19.232,"Carbon":18.007,"Nickel":14.5463,"Phosphorus":11.5284,"Zinc":5.22653,"Germanium":4.059,"Zirconium":2.23323,"Niobium":1.3144,"Tin":1.25155,"Ruthenium":1.1877},"updateTime":"2018-06-10 18:48:03"},{"id":8136013,"id64":1297036703160076651,"bodyId":36,"name":"(307261) 2002 MS4","discovery":{"commander":"Mini Valentine","date":"2017-09-29 20:09:09"},"type":"Planet","subType":"Icy body","offset":1,"parents":[{"Star":0}],"distanceToArrival":23805.351563,"isLandable":true,"gravity":0.013056696486296876,"earthMasses":0.00028,"radius":934,"surfaceTemperature":34,"surfacePressure":null,"volcanismType":"No volcanism","atmosphereType":"No atmosphere","atmosphereComposition":null,"solidComposition":{"Ice":60.0018,"Rock":26.934399999999997,"Metal":13.0638},"terraformingState":null,"orbitalPeriod":1886.15,"semiMajorAxis":41.71702990828732,"orbitalEccentricity":0.144,"orbitalInclination":17.677,"argOfPeriapsis":197.356552,"rotationalPeriod":1.3985687029861111,"rotationalPeriodTidallyLocked":false,"axialTilt":"-0.520425","materials":{"Sulphur":21.4998,"Carbon":18.0791,"Iron":16.1568,"Nickel":12.2203,"Phosphorus":11.5745,"Chromium":7.26625,"Manganese":6.67259,"Germanium":3.40997,"Niobium":1.10423,"Tin":1.05143,"Yttrium":0.965026},"updateTime":"2018-06-10 18:48:03"},{"id":3204253,"id64":1333065500179040619,"bodyId":37,"name":"Salacia","discovery":{"commander":"Mini Valentine","date":"2017-09-29 20:09:09"},"type":"Planet","subType":"Rocky Ice world","offset":1,"parents":[{"Star":0}],"distanceToArrival":18671.066406,"isLandable":true,"gravity":0.15617492993434942,"earthMasses":0.0028,"radius":854,"surfaceTemperature":34,"surfacePressure":null,"volcanismType":"No volcanism","atmosphereType":"No atmosphere","atmosphereComposition":null,"solidComposition":{"Rock":40.4022,"Ice":40.001799999999996,"Metal":19.596},"terraformingState":null,"orbitalPeriod":1895.88,"semiMajorAxis":41.860030093810686,"orbitalEccentricity":0.109,"orbitalInclination":23.936001,"argOfPeriapsis":18.199842,"rotationalPeriod":0.9910394965277778,"rotationalPeriodTidallyLocked":false,"axialTilt":"0.279863","materials":{"Sulphur":20.8471,"Iron":18.7228,"Carbon":17.5302,"Nickel":14.1611,"Phosphorus":11.2232,"Chromium":8.42027,"Selenium":3.26275,"Zirconium":2.1741,"Niobium":1.2796,"Molybdenum":1.22259,"Ruthenium":1.15625},"updateTime":"2018-06-10 18:48:03"},{"id":3198149,"id64":1369094297198004587,"bodyId":38,"name":"Actaea","discovery":{"commander":"Mini Valentine","date":"2017-09-29 20:09:09"},"type":"Planet","subType":"Rocky Ice world","offset":2,"parents":[{"Planet":37},{"Star":0}],"distanceToArrival":18671.054688,"isLandable":true,"gravity":0.001329244975982747,"earthMasses":3.0e-6,"radius":303,"surfaceTemperature":34,"surfacePressure":null,"volcanismType":"Major Water Geysers","atmosphereType":"No atmosphere","atmosphereComposition":null,"solidComposition":{"Rock":40.4022,"Ice":40.001799999999996,"Metal":19.596},"terraformingState":null,"orbitalPeriod":5.489999638310185,"semiMajorAxis":3.756068835543927e-5,"orbitalEccentricity":0.0084,"orbitalInclination":4.81822,"argOfPeriapsis":179.364548,"rotationalPeriod":0.9169088179976852,"rotationalPeriodTidallyLocked":true,"axialTilt":"0.234474","materials":{"Sulphur":19.5557,"Iron":17.563,"Carbon":16.4443,"Nickel":13.2839,"Phosphorus":10.5279,"Chromium":7.89866,"Manganese":7.25334,"Vanadium":4.31286,"Molybdenum":1.14685,"Yttrium":1.04902,"Tungsten":0.964385},"updateTime":"2018-06-10 18:48:03"},{"id":8136006,"id64":1405123094216968555,"bodyId":39,"name":"Haumea","discovery":{"commander":"Mini Valentine","date":"2017-09-29 20:09:09"},"type":"Planet","subType":"Icy body","offset":1,"parents":[{"Star":0}],"distanceToArrival":17599.269531,"isLandable":true,"gravity":0.06984407762747137,"earthMasses":0.00066,"radius":620,"surfaceTemperature":33,"surfacePressure":null,"volcanismType":"No volcanism","atmosphereType":"No atmosphere","atmosphereComposition":null,"solidComposition":{"Ice":60.0018,"Rock":26.934399999999997,"Metal":13.0638},"terraformingState":null,"orbitalPeriod":1988.84,"semiMajorAxis":43.21802893917794,"orbitalEccentricity":0.19126,"orbitalInclination":28.190001,"argOfPeriapsis":27.453764,"rotationalPeriod":0.16300000225694444,"rotationalPeriodTidallyLocked":false,"axialTilt":"0.226119","materials":{"Sulphur":21.3758,"Carbon":17.9749,"Iron":16.0637,"Nickel":12.1499,"Phosphorus":11.5078,"Chromium":7.22436,"Manganese":6.63412,"Zinc":4.3655,"Cadmium":1.24741,"Tungsten":0.882056,"Technetium":0.574532},"updateTime":"2018-06-10 18:48:03"},{"id":8136016,"id64":1441151891235932523,"bodyId":40,"name":"Hi'iaka","discovery":{"commander":"Mini Valentine","date":"2017-09-29 20:09:09"},"type":"Planet","subType":"Icy body","offset":2,"parents":[{"Planet":39},{"Star":0}],"distanceToArrival":17599.240234,"isLandable":true,"gravity":0.48306174749999997,"earthMasses":0.000304,"radius":160,"surfaceTemperature":33,"surfacePressure":null,"volcanismType":"No volcanism","atmosphereType":"No atmosphere","atmosphereComposition":null,"solidComposition":{"Ice":60.0018,"Rock":26.934399999999997,"Metal":13.0638},"terraformingState":null,"orbitalPeriod":49.12,"semiMajorAxis":0.0003334271521820531,"orbitalEccentricity":0.0513,"orbitalInclination":126.356003,"argOfPeriapsis":210.047256,"rotationalPeriod":49.94947916666667,"rotationalPeriodTidallyLocked":true,"axialTilt":"0.306352","materials":{"Sulphur":21.5845,"Carbon":18.1503,"Iron":16.2205,"Nickel":12.2685,"Phosphorus":11.6202,"Chromium":7.29488,"Manganese":6.69889,"Vanadium":3.98318,"Tungsten":0.890667,"Mercury":0.708321,"Technetium":0.580141},"updateTime":"2018-06-10 18:48:03"},{"id":8136008,"id64":1477180688254896491,"bodyId":41,"name":"Quaoar","discovery":{"commander":"Mini Valentine","date":"2017-09-29 20:09:09"},"type":"Planet","subType":"Rocky Ice world","offset":1,"parents":[{"Star":0}],"distanceToArrival":21418.652344,"isLandable":true,"gravity":0.008252325021066759,"earthMasses":0.000234,"radius":1074,"surfaceTemperature":33,"surfacePressure":null,"volcanismType":"No volcanism","atmosphereType":"No atmosphere","atmosphereComposition":null,"solidComposition":{"Rock":40.4022,"Ice":40.001799999999996,"Metal":19.596},"terraformingState":null,"orbitalPeriod":1999.55,"semiMajorAxis":43.37303254688638,"orbitalEccentricity":0.034,"orbitalInclination":7.987,"argOfPeriapsis":14.944939,"rotationalPeriod":1.527256763599537,"rotationalPeriodTidallyLocked":false,"axialTilt":"0.005212","materials":{"Sulphur":20.6874,"Iron":18.5794,"Carbon":17.3959,"Nickel":14.0526,"Phosphorus":11.1372,"Manganese":7.67309,"Zinc":5.04917,"Arsenic":1.75364,"Cadmium":1.44277,"Molybdenum":1.21322,"Tellurium":1.01562},"updateTime":"2018-06-10 18:48:03"},{"id":8136007,"id64":1513209485273860459,"bodyId":42,"name":"Makemake","discovery":{"commander":"Mini Valentine","date":"2017-09-29 20:09:09"},"type":"Planet","subType":"Icy body","offset":1,"parents":[{"Star":0}],"distanceToArrival":20363.910156,"isLandable":true,"gravity":0.058564543251992764,"earthMasses":0.000736,"radius":715,"surfaceTemperature":32,"surfacePressure":null,"volcanismType":"No volcanism","atmosphereType":"No atmosphere","atmosphereComposition":null,"solidComposition":{"Ice":60.0018,"Rock":26.934399999999997,"Metal":13.0638},"terraformingState":null,"orbitalPeriod":2163.63,"semiMajorAxis":45.71503163952453,"orbitalEccentricity":0.15586,"orbitalInclination":29.006849,"argOfPeriapsis":305.57251,"rotationalPeriod":0.3237916621412037,"rotationalPeriodTidallyLocked":false,"axialTilt":"0.513248","materials":{"Sulphur":22.0284,"Carbon":18.5236,"Iron":16.554,"Nickel":12.5208,"Phosphorus":11.8591,"Manganese":6.83665,"Zinc":4.49877,"Vanadium":4.0651,"Niobium":1.13138,"Tin":1.07728,"Tellurium":0.904904},"updateTime":"2018-06-10 18:48:03"},{"id":8136012,"id64":1549238282292824427,"bodyId":43,"name":"(225088) 2007 OR10","discovery":{"commander":"Mini Valentine","date":"2017-09-29 20:09:09"},"type":"Planet","subType":"Icy body","offset":1,"parents":[{"Star":0}],"distanceToArrival":49885.863281,"isLandable":true,"gravity":0.010800362878417968,"earthMasses":0.000435,"radius":1280,"surfaceTemperature":27,"surfacePressure":null,"volcanismType":"No volcanism","atmosphereType":"No atmosphere","atmosphereComposition":null,"solidComposition":{"Ice":60.0018,"Rock":26.934399999999997,"Metal":13.0638},"terraformingState":null,"orbitalPeriod":3832.57,"semiMajorAxis":66.92504709870848,"orbitalEccentricity":0.5066,"orbitalInclination":30.943001,"argOfPeriapsis":179.261887,"rotationalPeriod":1.085602394386574,"rotationalPeriodTidallyLocked":false,"axialTilt":"-0.035142","materials":{"Sulphur":22.7224,"Carbon":19.1072,"Iron":17.0756,"Nickel":12.9153,"Phosphorus":12.2328,"Chromium":7.67946,"Germanium":3.60389,"Arsenic":1.61171,"Cadmium":1.326,"Molybdenum":1.11503,"Technetium":0.610725},"updateTime":"2018-06-10 18:48:03"},{"id":8136011,"id64":1585267079311788395,"bodyId":44,"name":"Eris","discovery":{"commander":"Mini Valentine","date":"2017-09-29 20:09:09"},"type":"Planet","subType":"Icy body","offset":1,"parents":[{"Star":0}],"distanceToArrival":31116.248047,"isLandable":true,"gravity":0.08421076869276171,"earthMasses":0.0028,"radius":1163,"surfaceTemperature":26,"surfacePressure":null,"volcanismType":"No volcanism","atmosphereType":"No atmosphere","atmosphereComposition":null,"solidComposition":{"Ice":60.0018,"Rock":26.934399999999997,"Metal":13.0638},"terraformingState":null,"orbitalPeriod":3906.2796296296297,"semiMajorAxis":67.78104355272752,"orbitalEccentricity":0.44,"orbitalInclination":44.044498,"argOfPeriapsis":91.965385,"rotationalPeriod":1.0791666666666666,"rotationalPeriodTidallyLocked":false,"axialTilt":"-0.302889","materials":{"Sulphur":23.6868,"Carbon":19.9182,"Iron":17.8003,"Nickel":13.4634,"Phosphorus":12.752,"Germanium":3.75685,"Selenium":3.70719,"Arsenic":1.68011,"Tin":1.15838,"Ruthenium":1.09929,"Tungsten":0.977418},"updateTime":"2018-06-10 18:48:03"},{"id":8136015,"id64":1621295876330752363,"bodyId":45,"name":"Sedna","discovery":{"commander":"Mini Valentine","date":"2017-09-29 20:09:09"},"type":"Planet","subType":"Icy body","offset":1,"parents":[{"Star":0}],"distanceToArrival":467927.375,"isLandable":true,"gravity":0.017873603737279357,"earthMasses":0.000435,"radius":995,"surfaceTemperature":20,"surfacePressure":null,"volcanismType":"No volcanism","atmosphereType":"No atmosphere","atmosphereComposition":null,"solidComposition":{"Ice":60.0018,"Rock":26.934399999999997,"Metal":13.0638},"terraformingState":null,"orbitalPeriod":79800,"semiMajorAxis":506.2003718453728,"orbitalEccentricity":0.854,"orbitalInclination":30.943001,"argOfPeriapsis":264.631866,"rotationalPeriod":1.7770081018518518,"rotationalPeriodTidallyLocked":false,"axialTilt":"0.359275","materials":{"Sulphur":22.5915,"Carbon":18.9971,"Iron":16.9772,"Nickel":12.8409,"Phosphorus":12.1623,"Manganese":7.01142,"Vanadium":4.16902,"Zirconium":1.97141,"Niobium":1.1603,"Tin":1.10482,"Yttrium":1.01403},"updateTime":"2018-06-10 18:48:03"},{"id":8136018,"id64":1657324673349716331,"bodyId":46,"name":"Persephone","discovery":{"commander":"Mini Valentine","date":"2017-09-29 20:09:09"},"type":"Planet","subType":"Icy body","offset":1,"parents":[{"Star":0}],"distanceToArrival":456096.84375,"isLandable":true,"gravity":1.954317076274715,"earthMasses":9.9997,"radius":14427.148,"surfaceTemperature":20,"surfacePressure":null,"volcanismType":"Water Geysers","atmosphereType":"No atmosphere","atmosphereComposition":null,"solidComposition":{"Ice":60.0018,"Rock":26.934399999999997,"Metal":13.0638},"terraformingState":null,"orbitalPeriod":105000,"semiMajorAxis":700.0004979898688,"orbitalEccentricity":0.6,"orbitalInclination":30,"argOfPeriapsis":246.052597,"rotationalPeriod":1.0946168800694445,"rotationalPeriodTidallyLocked":false,"axialTilt":"-0.345941","materials":{"Sulphur":22.3376,"Carbon":18.7836,"Iron":16.7864,"Nickel":12.6966,"Phosphorus":12.0256,"Manganese":6.93263,"Germanium":3.54286,"Selenium":3.49603,"Cadmium":1.30354,"Tin":1.0924,"Yttrium":1.00263},"updateTime":"2018-06-10 18:48:03"}]}